confgetti/__init__.py
confgetti/base.py
confgetti/exceptions.py
confgetti/load.py
confgetti/logger.py
confgetti/remote.py
confgetti-0.1.13.dist-info/LICENSE
confgetti-0.1.13.dist-info/WHEEL
confgetti-0.1.13.dist-info/METADATA
confgetti-0.1.13.dist-info/RECORD
